goje_scrapper/__init__.py
goje_scrapper/goje.py
Goje-0.1.6.dist-info/LICENSE.txt
Goje-0.1.6.dist-info/METADATA
Goje-0.1.6.dist-info/WHEEL
Goje-0.1.6.dist-info/top_level.txt
Goje-0.1.6.dist-info/RECORD
