Metadata-Version: 2.1
Name: Goje
Version: 0.1.6
Summary: Unofficial Library for Scrapping Rotten Tomato.
Home-page: https://github.com/alifzl/goje_scrapper
Author: Ali Fazeli
Author-email: a.fazeli95@gmail.com
License: MIT
Keywords: scrapper
Platform: UNKNOWN
Classifier: Development Status :: 6 - Mature
Classifier: Intended Audience :: Developers
Classifier: Operating System :: OS Independent
Classifier: License :: OSI Approved :: MIT License
Classifier: Natural Language :: English
Classifier: Programming Language :: Python :: 3
Classifier: Topic :: Internet
Classifier: Topic :: Software Development :: Libraries
Classifier: Topic :: Software Development :: Testing
Classifier: Topic :: Text Processing
Classifier: Topic :: Utilities
Requires-Dist: requests
Requires-Dist: beautifulsoup4
Requires-Dist: lxml
Requires-Dist: selenium
